skdag/__init__.py
skdag/_version.py
skdag/exceptions.py
skdag/dag/__init__.py
skdag/dag/_builder.py
skdag/dag/_dag.py
skdag/dag/_render.py
skdag/dag/_utils.py
skdag/dag/tests/__init__.py
skdag/dag/tests/test_builder.py
skdag/dag/tests/test_dag.py
skdag/dag/tests/utils.py
skdag-0.0.7.dist-info/LICENSE
skdag-0.0.7.dist-info/METADATA
skdag-0.0.7.dist-info/WHEEL
skdag-0.0.7.dist-info/top_level.txt
skdag-0.0.7.dist-info/RECORD
